py_netgames_client/_base/BaseWebsocketProxy.py
py_netgames_client/_base/__init__.py
py_netgames_client/id/IdentifierFileGenerator.py
py_netgames_client/id/__init__.py
py_netgames_client/pygame_client/PyNetgamesServerProxy.py
py_netgames_client/pygame_client/__init__.py
py_netgames_client/tkinter_client/PyNetgamesServerListener.py
py_netgames_client/tkinter_client/PyNetgamesServerProxy.py
py_netgames_client/tkinter_client/__init__.py
py_netgames_client-0.0.5.dist-info/LICENSE.txt
py_netgames_client-0.0.5.dist-info/METADATA
py_netgames_client-0.0.5.dist-info/WHEEL
py_netgames_client-0.0.5.dist-info/top_level.txt
py_netgames_client-0.0.5.dist-info/RECORD
