Metadata-Version: 2.1
Name: py-netgames-client
Version: 0.0.5
Summary: Py-NetGames Client
Author-email: Gabriel Machado da Roza <gabrielmachadodaroza@outlook.com>
License: MIT License
License-File: LICENSE.txt
Requires-Dist: py-netgames-server
Requires-Dist: pygame
